[
    {
        "Judul": "Hamas Buktikan Diri Masih Kuat, Bunuh dan Lukai Tentara Israel 10 Lebih",
        "Link": "https://khazanah.republika.co.id/berita/snikue320/hamas-buktikan-diri-masih-kuat-bunuh-dan-lukai-tentara-israel-10-lebih",
        "Kategori": "Khazanah",
        "Waktu Terbit": "25 November 2024 23:09:04",
        "Waktu Scrapping": "25 November 2024 23:17:04",
        "Penulis": "Nashih Nashrullah"
    },
    {
        "Judul": "Segera IPO, MR.DIY Pasang Harga Awal Rp 1.650-Rp 1.870 per Saham",
        "Link": "https://ekonomi.republika.co.id/berita/sni5bn370/segera-ipo-mrdiy-pasang-harga-awal-rp-1650rp-1870-per-saham",
        "Kategori": "Ekonomi",
        "Waktu Terbit": "25 November 2024 23:00:05",
        "Waktu Scrapping": "25 November 2024 23:17:05",
        "Penulis": "Friska Yolandha"
    },
    {
        "Judul": "Banjir Rendam Permukiman Warga di Pekalongan",
        "Link": "https://visual.republika.co.id/berita/snihnq375/banjir-rendam-permukiman-warga-di-pekalongan",
        "Kategori": "Visual",
        "Waktu Terbit": "25 November 2024 23:00:05",
        "Waktu Scrapping": "25 November 2024 23:17:05",
        "Penulis": "Edwin Dwi Putranto"
    },
    {
        "Judul": "Amerika Serikat Ancam Mundur dari Perantara Mediasi Israel dan Lebanon, Ada Apa?",
        "Link": "https://news.republika.co.id/berita/snijue320/amerika-serikat-ancam-mundur-dari-perantara-mediasi-israel-dan-lebanon-ada-apa",
        "Kategori": "News",
        "Waktu Terbit": "25 November 2024 22:47:06",
        "Waktu Scrapping": "25 November 2024 23:17:06",
        "Penulis": "Nashih Nashrullah"
    },
    {
        "Judul": "Webinar COMNECTION 2024: Pentingnya Etika Jurnalistik di Era Digital",
        "Link": "https://news.republika.co.id/berita/snhnc8349/webinar-comnection-2024-pentingnya-etika-jurnalistik-di-era-digital",
        "Kategori": "News",
        "Waktu Terbit": "25 November 2024 22:45:06",
        "Waktu Scrapping": "25 November 2024 23:17:06",
        "Penulis": "Ichsan Emrald Alamsyah"
    },
    {
        "Judul": "Deklarasi Pilkada Damai, Wali Kota Depok Ajak Warga Wujudkan Suasana Aman dan Damai",
        "Link": "https://ruzkaindonesia.id/posts/489535/deklarasi-pilkada-damai-wali-kota-depok-ajak-warga-wujudkan-suasana-aman-dan-damai",
        "Kategori": "Network",
        "Waktu Terbit": "25 November 2024 22:41:07",
        "Waktu Scrapping": "25 November 2024 23:17:07",
        "Penulis": "-"
    },
    {
        "Judul": "Bawaslu Kota Depok Gelar Patroli Pengawasan saat Masa Tenang Pilkada",
        "Link": "https://ruzkaindonesia.id/posts/489549/bawaslu-kota-depok-gelar-patroli-pengawasan-saat-masa-tenang-pilkada",
        "Kategori": "Network",
        "Waktu Terbit": "25 November 2024 22:41:08",
        "Waktu Scrapping": "25 November 2024 23:17:08",
        "Penulis": "-"
    },
    {
        "Judul": "Prihatin Atas Perang Gaza, Perayaan Natal di Palestina akan Digelar Sederhana",
        "Link": "https://khazanah.republika.co.id/berita/snij50320/prihatin-atas-perang-gaza-perayaan-natal-di-palestina-akan-digelar-sederhana",
        "Kategori": "Khazanah",
        "Waktu Terbit": "25 November 2024 22:32:10",
        "Waktu Scrapping": "25 November 2024 23:17:10",
        "Penulis": "Nashih Nashrullah"
    },
    {
        "Judul": "Melihat Lebih Dekat Ratusan Koleksi Keris di Pameran Pesona Keris Nusantara",
        "Link": "https://visual.republika.co.id/berita/snihkk375/melihat-lebih-dekat-ratusan-koleksi-keris-di-pameran-pesona-keris-nusantara",
        "Kategori": "Visual",
        "Waktu Terbit": "25 November 2024 22:30:10",
        "Waktu Scrapping": "25 November 2024 23:17:10",
        "Penulis": "Edwin Dwi Putranto"
    },
    {
        "Judul": "Zurich Indonesia Catatkan Pertumbuhan Positif Tiga Sektor Ini",
        "Link": "https://ekonomi.republika.co.id/berita/sni78o370/zurich-indonesia-catatkan-pertumbuhan-positif-tiga-sektor-ini",
        "Kategori": "Ekonomi",
        "Waktu Terbit": "25 November 2024 22:30:11",
        "Waktu Scrapping": "25 November 2024 23:17:11",
        "Penulis": "Friska Yolandha"
    },
    {
        "Judul": "Laznas Dewan Dakwah Salurkan Bantuan Kemanusiaan Tahap 24 Melalui Yordania",
        "Link": "https://khazanah.republika.co.id/berita/sniilw320/laznas-dewan-dakwah-salurkan-bantuan-kemanusiaan-tahap-24-melalui-yordania",
        "Kategori": "Khazanah",
        "Waktu Terbit": "25 November 2024 22:20:11",
        "Waktu Scrapping": "25 November 2024 23:17:11",
        "Penulis": "Nashih Nashrullah"
    },
    {
        "Judul": "Menhan Negara ASEAN Lakukan Pertemuan Dengan AS dan Cina di Laos",
        "Link": "https://tv.republika.co.id/berita/snifit467/menhan-negara-asean-lakukan-pertemuan-dengan-as-dan-cina-di-laos",
        "Kategori": "Video",
        "Waktu Terbit": "25 November 2024 22:17:11",
        "Waktu Scrapping": "25 November 2024 23:17:11",
        "Penulis": "Wisnu Aji Prasetiyo"
    },
    {
        "Judul": "KPEI Sosialisasikan CCP PUVA, Ajak Perbankan Jadi Anggota",
        "Link": "https://ekonomi.republika.co.id/berita/sni4jk370/kpei-sosialisasikan-ccp-puva-ajak-perbankan-jadi-anggota",
        "Kategori": "Ekonomi",
        "Waktu Terbit": "25 November 2024 22:17:13",
        "Waktu Scrapping": "25 November 2024 23:17:13",
        "Penulis": "Friska Yolandha"
    },
    {
        "Judul": "Polda Riau Sita dan Segel Rumah Muflihun, Diduga Terkait Korupsi SPPD Fiktif",
        "Link": "https://news.republika.co.id/berita/snhqca451/polda-riau-sita-dan-segel-rumah-muflihun-diduga-terkait-korupsi-sppd-fiktif",
        "Kategori": "News",
        "Waktu Terbit": "25 November 2024 22:17:13",
        "Waktu Scrapping": "25 November 2024 23:17:13",
        "Penulis": "Erdy Nasrul"
    },
    {
        "Judul": "Jelang Pencoblosan Pilkada, Calon Tunggal Wakil Bupati Ciamis Meninggal Dunia",
        "Link": "https://visual.republika.co.id/berita/snihcl375/jelang-pencoblosan-pilkada-calon-tunggal-wakil-bupati-ciamis-meninggal-dunia",
        "Kategori": "Visual",
        "Waktu Terbit": "25 November 2024 22:17:14",
        "Waktu Scrapping": "25 November 2024 23:17:14",
        "Penulis": "Edwin Dwi Putranto"
    },
    {
        "Judul": "Ditjen Pajak: Semua Buku Bebas PPN, Kecuali Langgar Hukum",
        "Link": "https://news.republika.co.id/berita/snihh0484/ditjen-pajak-semua-buku-bebas-ppn-kecuali-langgar-hukum",
        "Kategori": "News",
        "Waktu Terbit": "25 November 2024 22:17:16",
        "Waktu Scrapping": "25 November 2024 23:17:16",
        "Penulis": "Erik Purnama Putra"
    },
    {
        "Judul": "Munculnya Api Besar di Tanah Hijaz Tanda Kiamat, Apakah Sudah Terjadi?",
        "Link": "https://iqra.republika.co.id/berita/snihf3320/munculnya-api-besar-di-tanah-hijaz-tanda-kiamat-apakah-sudah-terjadi",
        "Kategori": "Iqra",
        "Waktu Terbit": "25 November 2024 22:17:17",
        "Waktu Scrapping": "25 November 2024 23:17:17",
        "Penulis": "Nashih Nashrullah"
    },
    {
        "Judul": "Dua Hari Jelang Pencoblosan Pilkada, Jabar Gelar Doa Lintas Agama Ini Tujuannya",
        "Link": "https://rejabar.republika.co.id/berita/snih5w512/dua-hari-jelang-pencoblosan-pilkada-jabar-gelar-doa-lintas-agama-ini-tujuannya",
        "Kategori": "Rejabar",
        "Waktu Terbit": "25 November 2024 22:17:18",
        "Waktu Scrapping": "25 November 2024 23:17:18",
        "Penulis": "Arie Lukihardianti"
    },
    {
        "Judul": "Dua Petani Indramayu Tewas Tersambar Petir Saat Berteduh di Gubuk Sawah, Ini Kronologinya",
        "Link": "https://news.republika.co.id/berita/snih21409/dua-petani-indramayu-tewas-tersambar-petir-saat-berteduh-di-gubuk-sawah-ini-kronologinya",
        "Kategori": "News",
        "Waktu Terbit": "25 November 2024 21:17:20",
        "Waktu Scrapping": "25 November 2024 23:17:20",
        "Penulis": "Andri Saubani"
    },
    {
        "Judul": "Korsel dan Malaysia Perluas Kerja Sama di Bidang Industri Pertahanan",
        "Link": "https://news.republika.co.id/berita/snigrg484/korsel-dan-malaysia-perluas-kerja-sama-di-bidang-industri-pertahanan",
        "Kategori": "News",
        "Waktu Terbit": "25 November 2024 21:17:21",
        "Waktu Scrapping": "25 November 2024 23:17:21",
        "Penulis": "Erik Purnama Putra"
    },
    {
        "Judul": "Tiga Terdakwa Kasus Pembunuhan Wartawan di Karo Jalani Sidang Perdana",
        "Link": "https://visual.republika.co.id/berita/snigr1375/tiga-terdakwa-kasus-pembunuhan-wartawan-di-karo-jalani-sidang-perdana",
        "Kategori": "Visual",
        "Waktu Terbit": "25 November 2024 21:17:22",
        "Waktu Scrapping": "25 November 2024 23:17:22",
        "Penulis": "Edwin Dwi Putranto"
    },
    {
        "Judul": "Proses Perekrutan ASN dengan Manajemen Talenta, Dinilai Bisa Cegah Politisasi Birokrasi",
        "Link": "https://rejabar.republika.co.id/berita/snignz512/proses-perekrutan-asn-dengan-manajemen-talenta-dinilai-bisa-cegah-politisasi-birokrasi",
        "Kategori": "Rejabar",
        "Waktu Terbit": "25 November 2024 21:17:23",
        "Waktu Scrapping": "25 November 2024 23:17:23",
        "Penulis": "Arie Lukihardianti"
    },
    {
        "Judul": "Cedera Hamstring, Vinicius Absen pada Laga Liga Champions Vs Liverpool",
        "Link": "https://news.republika.co.id/berita/snight409/cedera-hamstring-vinicius-absen-pada-laga-liga-champions-vs-liverpool",
        "Kategori": "News",
        "Waktu Terbit": "25 November 2024 21:17:24",
        "Waktu Scrapping": "25 November 2024 23:17:24",
        "Penulis": "Andri Saubani"
    },
    {
        "Judul": "Presiden Marcos Akhirnya Bersuara Setelah Diancam Dibunuh Wapres",
        "Link": "https://news.republika.co.id/berita/snigbw484/presiden-marcos-akhirnya-bersuara-setelah-diancam-dibunuh-wapres",
        "Kategori": "News",
        "Waktu Terbit": "25 November 2024 21:17:26",
        "Waktu Scrapping": "25 November 2024 23:17:26",
        "Penulis": "Erik Purnama Putra"
    },
    {
        "Judul": "Warga Buka Paksa Bantalan Beton yang Tutup Perlintasan Rel Kereta Api Ciroyom",
        "Link": "https://rejabar.republika.co.id/berita/snifyt512/warga-buka-paksa-bantalan-beton-yang-tutup-perlintasan-rel-kereta-api-ciroyom",
        "Kategori": "Rejabar",
        "Waktu Terbit": "25 November 2024 21:17:26",
        "Waktu Scrapping": "25 November 2024 23:17:26",
        "Penulis": "Arie Lukihardianti"
    },
    {
        "Judul": "LBH Gema Keadilan Instruksikan Seluruh Aktivis Kawal Pencoblosan hingga Rekapitulasi",
        "Link": "https://news.republika.co.id/berita/snifie320/lbh-gema-keadilan-instruksikan-seluruh-aktivis-kawal-pencoblosan-hingga-rekapitulasi",
        "Kategori": "News",
        "Waktu Terbit": "25 November 2024 21:17:27",
        "Waktu Scrapping": "25 November 2024 23:17:27",
        "Penulis": "Nashih Nashrullah"
    },
    {
        "Judul": "Peredaran Sabu di Lapas Indramayu Terbongkar",
        "Link": "https://rejabar.republika.co.id/berita/snifdb512/peredaran-sabu-di-lapas-indramayu-terbongkar",
        "Kategori": "Rejabar",
        "Waktu Terbit": "25 November 2024 21:17:28",
        "Waktu Scrapping": "25 November 2024 23:17:28",
        "Penulis": "Arie Lukihardianti"
    },
    {
        "Judul": "Wanita Ini Menjadi Salah Satu Guru Imam Syafii yang Paling Berjasa",
        "Link": "https://khazanah.republika.co.id/berita/snierg430/wanita-ini-menjadi-salah-satu-guru-imam-syafii-yang-paling-berjasa",
        "Kategori": "Khazanah",
        "Waktu Terbit": "25 November 2024 21:17:30",
        "Waktu Scrapping": "25 November 2024 23:17:30",
        "Penulis": "Muhammad Hafil"
    },
    {
        "Judul": "Turki Berkomitmen Perkuat Kerja Sama Dengan Indonesia",
        "Link": "https://tv.republika.co.id/berita/snieom467/turki-berkomitmen-perkuat-kerja-sama-dengan-indonesia",
        "Kategori": "Video",
        "Waktu Terbit": "25 November 2024 21:17:30",
        "Waktu Scrapping": "25 November 2024 23:17:30",
        "Penulis": "Wisnu Aji Prasetiyo"
    },
    {
        "Judul": "Serangan Hizbullah Paling Besar Paksa Jutaan Warga Israel Sembunyi, Ini Kata Pakar Militer",
        "Link": "https://news.republika.co.id/berita/sniel4320/serangan-hizbullah-paling-besar-paksa-jutaan-warga-israel-sembunyi-ini-kata-pakar-militer",
        "Kategori": "News",
        "Waktu Terbit": "25 November 2024 21:17:32",
        "Waktu Scrapping": "25 November 2024 23:17:32",
        "Penulis": "Nashih Nashrullah"
    },
    {
        "Judul": "Kata-Kata Petuah Penuh Makna dari Imam Syafii",
        "Link": "https://khazanah.republika.co.id/berita/sniejg430/katakata-petuah-penuh-makna-dari-imam-syafii",
        "Kategori": "Khazanah",
        "Waktu Terbit": "25 November 2024 21:17:32",
        "Waktu Scrapping": "25 November 2024 23:17:32",
        "Penulis": "Muhammad Hafil"
    },
    {
        "Judul": "Kesombongan, Dosa yang Paling Dibenci",
        "Link": "https://khazanah.republika.co.id/berita/snie10458/kesombongan-dosa-yang-paling-dibenci",
        "Kategori": "Khazanah",
        "Waktu Terbit": "25 November 2024 20:17:34",
        "Waktu Scrapping": "25 November 2024 23:17:34",
        "Penulis": "Hasanul Rizqa"
    },
    {
        "Judul": "Menko Polkam dan Ketua KPU Pastikan Pilkada Serentak Siap Digelar",
        "Link": "https://visual.republika.co.id/berita/snidyw375/menko-polkam-dan-ketua-kpu-pastikan-pilkada-serentak-siap-digelar",
        "Kategori": "Visual",
        "Waktu Terbit": "25 November 2024 20:17:34",
        "Waktu Scrapping": "25 November 2024 23:17:34",
        "Penulis": "Edwin Dwi Putranto"
    },
    {
        "Judul": "Mengapa Imam Syafii Digelari Pembela Sunnah?",
        "Link": "https://khazanah.republika.co.id/berita/snidkj430/mengapa-imam-syafii-digelari-pembela-sunnah",
        "Kategori": "Khazanah",
        "Waktu Terbit": "25 November 2024 20:17:35",
        "Waktu Scrapping": "25 November 2024 23:17:35",
        "Penulis": "Muhammad Hafil"
    },
    {
        "Judul": "4 Amalan Paling Berat Timbangan Pahalanya Menurut Ali bin Abi Thalib",
        "Link": "https://khazanah.republika.co.id/berita/snidjy320/4-amalan-paling-berat-timbangan-pahalanya-menurut-ali-bin-abi-thalib",
        "Kategori": "Khazanah",
        "Waktu Terbit": "25 November 2024 20:17:36",
        "Waktu Scrapping": "25 November 2024 23:17:36",
        "Penulis": "Nashih Nashrullah"
    },
    {
        "Judul": "Imam Al Ghazali Kategorikan Barang-Barang Halal",
        "Link": "https://khazanah.republika.co.id/berita/snide4430/imam-al-ghazali-kategorikan-barangbarang-halal",
        "Kategori": "Khazanah",
        "Waktu Terbit": "25 November 2024 20:17:37",
        "Waktu Scrapping": "25 November 2024 23:17:37",
        "Penulis": "Muhammad Hafil"
    },
    {
        "Judul": "Ketika Warisan Nabi Dibagikan di Masjid",
        "Link": "https://khazanah.republika.co.id/berita/sniddx458/ketika-warisan-nabi-dibagikan-di-masjid",
        "Kategori": "Khazanah",
        "Waktu Terbit": "25 November 2024 20:17:38",
        "Waktu Scrapping": "25 November 2024 23:17:38",
        "Penulis": "Hasanul Rizqa"
    },
    {
        "Judul": "Pesona Volkswagen Tiguan Allspace Business di Gaikindo Jakarta Auto Week 2024",
        "Link": "https://ekonomi.republika.co.id/berita/snicwh349/pesona-volkswagen-tiguan-allspace-business-di-gaikindo-jakarta-auto-week-2024",
        "Kategori": "Ekonomi",
        "Waktu Terbit": "25 November 2024 20:17:39",
        "Waktu Scrapping": "25 November 2024 23:17:39",
        "Penulis": "Ichsan Emrald Alamsyah"
    },
    {
        "Judul": "Muslim Prancis Sebut Perintah ICC Tangkap Netanyahu Seperti Secercah Harapan",
        "Link": "https://khazanah.republika.co.id/berita/snicq9430/muslim-prancis-sebut-perintah-icc-tangkap-netanyahu-seperti-secercah-harapan",
        "Kategori": "Khazanah",
        "Waktu Terbit": "25 November 2024 20:17:40",
        "Waktu Scrapping": "25 November 2024 23:17:40",
        "Penulis": "Muhammad Hafil"
    },
    {
        "Judul": "Ke Jerman, Menkomdigi Perkuat Kerja Sama Internasional Demi Transformasi Digital",
        "Link": "https://ekonomi.republika.co.id/berita/snickp370/ke-jerman-menkomdigi-perkuat-kerja-sama-internasional-demi-transformasi-digital",
        "Kategori": "Ekonomi",
        "Waktu Terbit": "25 November 2024 20:17:41",
        "Waktu Scrapping": "25 November 2024 23:17:41",
        "Penulis": "Friska Yolandha"
    },
    {
        "Judul": "Bahlil Bertemu Menteri Investasi UEA di Abu Dhabi, Bahas Tiga Hal Ini",
        "Link": "https://ekonomi.republika.co.id/berita/snibp0370/bahlil-bertemu-menteri-investasi-uea-di-abu-dhabi-bahas-tiga-hal-ini",
        "Kategori": "Ekonomi",
        "Waktu Terbit": "25 November 2024 20:17:43",
        "Waktu Scrapping": "25 November 2024 23:17:43",
        "Penulis": "Friska Yolandha"
    },
    {
        "Judul": "Peduli Pada Isu Pendidikan, Mahasiswa\u00a0UNM Terpilih Jadi Duta Edukasi Jakarta 2024",
        "Link": "https://news.republika.co.id/berita/snibca370/peduli-pada-isu-pendidikan-mahasiswaunm-terpilih-jadi-duta-edukasi-jakarta-2024",
        "Kategori": "News",
        "Waktu Terbit": "25 November 2024 20:17:43",
        "Waktu Scrapping": "25 November 2024 23:17:43",
        "Penulis": "Friska Yolandha"
    },
    {
        "Judul": "Siswa SMK 4 Semarang Anggota Paskibra Tewas Diduga Ditembak Oknum Polisi",
        "Link": "https://rejogja.republika.co.id/berita/snic55282/siswa-smk-4-semarang-anggota-paskibra-tewas-diduga-ditembak-oknum-polisi",
        "Kategori": "Rejogja",
        "Waktu Terbit": "25 November 2024 20:17:44",
        "Waktu Scrapping": "25 November 2024 23:17:44",
        "Penulis": "Karta Raharja Ucu"
    },
    {
        "Judul": "Peran Kerajaan Sriwijaya dalam Penyebaran Islam di Nusantara",
        "Link": "https://khazanah.republika.co.id/berita/snibzy458/peran-kerajaan-sriwijaya-dalam-penyebaran-islam-di-nusantara",
        "Kategori": "Khazanah",
        "Waktu Terbit": "25 November 2024 20:17:45",
        "Waktu Scrapping": "25 November 2024 23:17:45",
        "Penulis": "Hasanul Rizqa"
    },
    {
        "Judul": "Modal Tipis? Ini Cara Sukses Berwirausaha ala BSI Entrepreneur Center!",
        "Link": "https://news.republika.co.id/berita/snib8q370/modal-tipis-ini-cara-sukses-berwirausaha-ala-bsi-entrepreneur-center",
        "Kategori": "News",
        "Waktu Terbit": "25 November 2024 20:17:46",
        "Waktu Scrapping": "25 November 2024 23:17:46",
        "Penulis": "Friska Yolandha"
    },
    {
        "Judul": "Perkuat Kelistrikan Sumsel, PKN Rampungkan Pembangunan SUTT Lubuk Linggau-Tebing Tinggi",
        "Link": "https://ekonomi.republika.co.id/berita/snibik370/perkuat-kelistrikan-sumsel-pkn-rampungkan-pembangunan-sutt-lubuk-linggautebing-tinggi",
        "Kategori": "Ekonomi",
        "Waktu Terbit": "25 November 2024 19:17:48",
        "Waktu Scrapping": "25 November 2024 23:17:48",
        "Penulis": "Friska Yolandha"
    },
    {
        "Judul": "Kampus Tertua di Dunia Ini Langgeng Berkat Wakaf",
        "Link": "https://khazanah.republika.co.id/berita/snibeu458/kampus-tertua-di-dunia-ini-langgeng-berkat-wakaf",
        "Kategori": "Khazanah",
        "Waktu Terbit": "25 November 2024 19:17:48",
        "Waktu Scrapping": "25 November 2024 23:17:48",
        "Penulis": "Hasanul Rizqa"
    },
    {
        "Judul": "Pasukan TNI UNIFIL di Lebanon yang Teguh, Meski Diserang Israel",
        "Link": "https://news.republika.co.id/berita/snibde484/pasukan-tni-unifil-di-lebanon-yang-teguh-meski-diserang-israel",
        "Kategori": "News",
        "Waktu Terbit": "25 November 2024 19:17:49",
        "Waktu Scrapping": "25 November 2024 23:17:49",
        "Penulis": "Erik Purnama Putra"
    },
    {
        "Judul": "Stop Kriminalisasi Guru, Cukup Supriyani yang Terakhir",
        "Link": "https://kingdomsriwijaya.id/posts/489526/stop-kriminalisasi-guru-cukup-supriyani-yang-terakhir",
        "Kategori": "Network",
        "Waktu Terbit": "25 November 2024 19:17:50",
        "Waktu Scrapping": "25 November 2024 23:17:50",
        "Penulis": "-"
    },
    {
        "Judul": "Kisah Guru Honorer Warkina, Rela Kerja Keras Cari Sampingan Buat Perpustakaan Keliling",
        "Link": "https://rejabar.republika.co.id/berita/snib5g512/kisah-guru-honorer-warkina-rela-kerja-keras-cari-sampingan-buat-perpustakaan-keliling",
        "Kategori": "Rejabar",
        "Waktu Terbit": "25 November 2024 19:17:52",
        "Waktu Scrapping": "25 November 2024 23:17:52",
        "Penulis": "Arie Lukihardianti"
    }
]